{
  "config": "{\"version\":\"5.57\",\"themeCollection\":{\"baseTheme\":{\"name\":\"CY24SU08\",\"version\":\"5.58\",\"type\":2},\"customTheme\":{\"name\":\"AccessibleNeutral\",\"version\":\"5.58\",\"type\":2}},\"activeSectionIndex\":0,\"defaultDrillFilterOtherVisuals\":true,\"linguisticSchemaSyncVersion\":2,\"settings\":{\"useNewFilterPaneExperience\":true,\"allowChangeFilterTypes\":true,\"useStylableVisualContainerHeader\":true,\"queryLimitOption\":6,\"exportDataMode\":1,\"useDefaultAggregateDisplayName\":true,\"useEnhancedTooltips\":true},\"objects\":{\"section\":[{\"properties\":{\"verticalAlignment\":{\"expr\":{\"Literal\":{\"Value\":\"'Top'\"}}}}}]}}",
  "filters": "[{\"name\":\"f2dcda7074e0a3272ca8\",\"expression\":{\"Column\":{\"Expression\":{\"SourceRef\":{\"Entity\":\"RLTR_DATA\"}},\"Property\":\"County\"}},\"filter\":{\"Version\":2,\"From\":[{\"Name\":\"r\",\"Entity\":\"RLTR_DATA\",\"Type\":0}],\"Where\":[{\"Condition\":{\"Not\":{\"Expression\":{\"In\":{\"Expressions\":[{\"Column\":{\"Expression\":{\"SourceRef\":{\"Source\":\"r\"}},\"Property\":\"County\"}}],\"Values\":[[{\"Literal\":{\"Value\":\"null\"}}],[{\"Literal\":{\"Value\":\"'Klickitat'\"}}],[{\"Literal\":{\"Value\":\"'Ascension Parish'\"}}]]}}}}}]},\"type\":\"Categorical\",\"howCreated\":1,\"objects\":{\"general\":[{\"properties\":{\"isInvertedSelectionMode\":{\"expr\":{\"Literal\":{\"Value\":\"true\"}}}}}]}}]",
  "layoutOptimization": 0,
  "pods": [
    {
      "boundSection": "d4f852bebde767e1b390",
      "config": "{}",
      "name": "d3592a77b364d7d8384b",
      "parameters": "[{\"name\":\"2021803b2f2ae5c938b1\",\"boundFilter\":\"e524298bdf96ec92f46f\",\"fieldExpr\":{\"Column\":{\"Expression\":{\"SourceRef\":{\"Entity\":\"RLTR_DATA\"}},\"Property\":\"Property Link\"}}}]",
      "type": 1
    }
  ],
  "resourcePackages": [
    {
      "resourcePackage": {
        "disabled": false,
        "items": [
          {
            "name": "AccessibleNeutral",
            "path": "BuiltInThemes/AccessibleNeutral.json",
            "type": 201
          },
          {
            "name": "CY24SU08",
            "path": "BaseThemes/CY24SU08.json",
            "type": 202
          }
        ],
        "name": "SharedResources",
        "type": 2
      }
    }
  ],
  "sections": [
    {
      "config": "{\"relationships\":[{\"source\":\"cf416eb4fd2224395989\",\"target\":\"7e422f0a109c91b6d092\",\"type\":3},{\"source\":\"cf416eb4fd2224395989\",\"target\":\"972af63a2cbd00b1f810\",\"type\":3},{\"source\":\"14a74295417b272b8c17\",\"target\":\"7e422f0a109c91b6d092\",\"type\":3},{\"source\":\"14a74295417b272b8c17\",\"target\":\"972af63a2cbd00b1f810\",\"type\":3}],\"objects\":{\"background\":[{\"properties\":{\"color\":{\"solid\":{\"color\":{\"expr\":{\"ThemeDataColor\":{\"ColorId\":1,\"Percent\":0}}}}}}}]}}",
      "displayName": "Page 1",
      "displayOption": 1,
      "filters": "[{\"name\":\"e524298bdf96ec92f46f\",\"expression\":{\"Column\":{\"Expression\":{\"SourceRef\":{\"Entity\":\"RLTR_DATA\"}},\"Property\":\"Property Link\"}},\"type\":\"Categorical\",\"howCreated\":5}]",
      "height": 720.00,
      "name": "d4f852bebde767e1b390",
      "visualContainers": [
        {
          "config": "{\"name\":\"04480a993fcab0ae7ad5\",\"layouts\":[{\"id\":0,\"position\":{\"x\":0,\"y\":285.6655290102389,\"z\":1000,\"width\":199.65870307167236,\"height\":52.83276450511946,\"tabOrder\":1000}}],\"singleVisual\":{\"visualType\":\"multiRowCard\",\"projections\":{\"Values\":[{\"queryRef\":\"Sum(RLTR_DATA.PRICE)\"}]},\"prototypeQuery\":{\"Version\":2,\"From\":[{\"Name\":\"r\",\"Entity\":\"RLTR_DATA\",\"Type\":0}],\"Select\":[{\"Aggregation\":{\"Expression\":{\"Column\":{\"Expression\":{\"SourceRef\":{\"Source\":\"r\"}},\"Property\":\"Price\"}},\"Function\":1},\"Name\":\"Sum(RLTR_DATA.PRICE)\",\"NativeReferenceName\":\"Average List Price\"}],\"OrderBy\":[{\"Direction\":2,\"Expression\":{\"Aggregation\":{\"Expression\":{\"Column\":{\"Expression\":{\"SourceRef\":{\"Source\":\"r\"}},\"Property\":\"Price\"}},\"Function\":1}}}]},\"columnProperties\":{\"Sum(RLTR_DATA.PRICE)\":{\"displayName\":\"Average List Price\"}},\"drillFilterOtherVisuals\":true,\"hasDefaultSort\":true,\"objects\":{\"categoryLabels\":[{\"properties\":{\"show\":{\"expr\":{\"Literal\":{\"Value\":\"true\"}}}}}]},\"vcObjects\":{\"title\":[{\"properties\":{\"show\":{\"expr\":{\"Literal\":{\"Value\":\"false\"}}},\"text\":{\"expr\":{\"Literal\":{\"Value\":\"'Average Price'\"}}}}}],\"background\":[{\"properties\":{\"show\":{\"expr\":{\"Literal\":{\"Value\":\"false\"}}}}}]}}}",
          "filters": "[]",
          "height": 52.83,
          "width": 199.66,
          "x": 0.00,
          "y": 285.67,
          "z": 1000.00
        },
        {
          "config": "{\"name\":\"086e0cdc7296105922b0\",\"layouts\":[{\"id\":0,\"position\":{\"x\":0,\"y\":339.7269624573379,\"z\":5000,\"width\":199.65870307167236,\"height\":52.83276450511946,\"tabOrder\":5000}}],\"singleVisual\":{\"visualType\":\"multiRowCard\",\"projections\":{\"Values\":[{\"queryRef\":\"Sum(RLTR_DATA.PRICE)\"}]},\"prototypeQuery\":{\"Version\":2,\"From\":[{\"Name\":\"r\",\"Entity\":\"RLTR_DATA\",\"Type\":0}],\"Select\":[{\"Aggregation\":{\"Expression\":{\"Column\":{\"Expression\":{\"SourceRef\":{\"Source\":\"r\"}},\"Property\":\"Price\"}},\"Function\":4},\"Name\":\"Sum(RLTR_DATA.PRICE)\",\"NativeReferenceName\":\"Highest List Price\"}],\"OrderBy\":[{\"Direction\":2,\"Expression\":{\"Aggregation\":{\"Expression\":{\"Column\":{\"Expression\":{\"SourceRef\":{\"Source\":\"r\"}},\"Property\":\"Price\"}},\"Function\":4}}}]},\"columnProperties\":{\"Sum(RLTR_DATA.PRICE)\":{\"displayName\":\"Highest List Price\"}},\"drillFilterOtherVisuals\":true,\"hasDefaultSort\":true,\"objects\":{\"categoryLabels\":[{\"properties\":{\"show\":{\"expr\":{\"Literal\":{\"Value\":\"true\"}}}}}]},\"vcObjects\":{\"title\":[{\"properties\":{\"show\":{\"expr\":{\"Literal\":{\"Value\":\"false\"}}},\"text\":{\"expr\":{\"Literal\":{\"Value\":\"'Average Price'\"}}}}}],\"background\":[{\"properties\":{\"show\":{\"expr\":{\"Literal\":{\"Value\":\"false\"}}}}}]}}}",
          "filters": "[]",
          "height": 52.83,
          "width": 199.66,
          "x": 0.00,
          "y": 339.73,
          "z": 5000.00
        },
        {
          "config": "{\"name\":\"0b5c92225f317cfd8e00\",\"layouts\":[{\"id\":0,\"position\":{\"x\":0,\"y\":128.39590443686006,\"z\":11000,\"width\":199.65870307167236,\"height\":52.83276450511946,\"tabOrder\":11000}}],\"singleVisual\":{\"visualType\":\"multiRowCard\",\"projections\":{\"Values\":[{\"queryRef\":\"CountNonNull(RLTR_DATA.UID)\"}]},\"prototypeQuery\":{\"Version\":2,\"From\":[{\"Name\":\"r\",\"Entity\":\"RLTR_DATA\",\"Type\":0}],\"Select\":[{\"Aggregation\":{\"Expression\":{\"Column\":{\"Expression\":{\"SourceRef\":{\"Source\":\"r\"}},\"Property\":\"UID\"}},\"Function\":2},\"Name\":\"CountNonNull(RLTR_DATA.UID)\",\"NativeReferenceName\":\"# of Properties\"}],\"OrderBy\":[{\"Direction\":2,\"Expression\":{\"Aggregation\":{\"Expression\":{\"Column\":{\"Expression\":{\"SourceRef\":{\"Source\":\"r\"}},\"Property\":\"UID\"}},\"Function\":2}}}]},\"columnProperties\":{\"CountNonNull(RLTR_DATA.UID)\":{\"displayName\":\"# of Properties\",\"formatString\":\"#,0\"}},\"drillFilterOtherVisuals\":true,\"hasDefaultSort\":true,\"objects\":{\"categoryLabels\":[{\"properties\":{\"show\":{\"expr\":{\"Literal\":{\"Value\":\"true\"}}}}}]},\"vcObjects\":{\"title\":[{\"properties\":{\"show\":{\"expr\":{\"Literal\":{\"Value\":\"false\"}}},\"text\":{\"expr\":{\"Literal\":{\"Value\":\"'Average Price'\"}}}}}],\"background\":[{\"properties\":{\"show\":{\"expr\":{\"Literal\":{\"Value\":\"false\"}}}}}]}}}",
          "filters": "[]",
          "height": 52.83,
          "width": 199.66,
          "x": 0.00,
          "y": 128.40,
          "z": 11000.00
        },
        {
          "config": "{\"name\":\"14a74295417b272b8c17\",\"layouts\":[{\"id\":0,\"position\":{\"x\":0.7835891406134625,\"y\":69.46201752225465,\"z\":12000,\"width\":301.6382252559727,\"height\":60.81911262798635,\"tabOrder\":12000}}],\"singleVisual\":{\"visualType\":\"slicer\",\"projections\":{\"Values\":[{\"queryRef\":\"RLTR_DATA.Status\",\"active\":true}]},\"prototypeQuery\":{\"Version\":2,\"From\":[{\"Name\":\"r\",\"Entity\":\"RLTR_DATA\",\"Type\":0}],\"Select\":[{\"Column\":{\"Expression\":{\"SourceRef\":{\"Source\":\"r\"}},\"Property\":\"Status\"},\"Name\":\"RLTR_DATA.Status\",\"NativeReferenceName\":\"Property Type\"}]},\"columnProperties\":{\"RLTR_DATA.Status\":{\"displayName\":\"Property Type\"}},\"drillFilterOtherVisuals\":true,\"objects\":{\"data\":[{\"properties\":{\"mode\":{\"expr\":{\"Literal\":{\"Value\":\"'Dropdown'\"}}}}}],\"general\":[{\"properties\":{\"selfFilterEnabled\":{\"expr\":{\"Literal\":{\"Value\":\"true\"}}}}}],\"header\":[{\"properties\":{\"show\":{\"expr\":{\"Literal\":{\"Value\":\"false\"}}}}}],\"items\":[{\"properties\":{\"textSize\":{\"expr\":{\"Literal\":{\"Value\":\"10D\"}}}}}]},\"vcObjects\":{\"title\":[{\"properties\":{\"show\":{\"expr\":{\"Literal\":{\"Value\":\"true\"}}},\"text\":{\"expr\":{\"Literal\":{\"Value\":\"'Select Property Type'\"}}},\"alignment\":{\"expr\":{\"Literal\":{\"Value\":\"'center'\"}}},\"fontSize\":{\"expr\":{\"Literal\":{\"Value\":\"10D\"}}}}}],\"background\":[{\"properties\":{\"show\":{\"expr\":{\"Literal\":{\"Value\":\"false\"}}}}}]}}}",
          "filters": "[{\"name\":\"5ce0f1c44cda63fba84d\",\"expression\":{\"Column\":{\"Expression\":{\"SourceRef\":{\"Entity\":\"RLTR_DATA\"}},\"Property\":\"County\"}},\"filter\":{\"Version\":2,\"From\":[{\"Name\":\"r\",\"Entity\":\"RLTR_DATA\",\"Type\":0}],\"Where\":[{\"Condition\":{\"Not\":{\"Expression\":{\"In\":{\"Expressions\":[{\"Column\":{\"Expression\":{\"SourceRef\":{\"Source\":\"r\"}},\"Property\":\"County\"}}],\"Values\":[[{\"Literal\":{\"Value\":\"null\"}}]]}}}}}]},\"type\":\"Categorical\",\"howCreated\":1,\"objects\":{\"general\":[{\"properties\":{\"isInvertedSelectionMode\":{\"expr\":{\"Literal\":{\"Value\":\"true\"}}}}}]},\"isHiddenInViewMode\":false}]",
          "height": 60.82,
          "width": 301.64,
          "x": 0.78,
          "y": 69.46,
          "z": 12000.00
        },
        {
          "config": "{\"name\":\"15c238f8f59f35ec95d4\",\"layouts\":[{\"id\":0,\"position\":{\"x\":0,\"y\":526.4846416382253,\"z\":7000,\"width\":199.65870307167236,\"height\":52.83276450511946,\"tabOrder\":7000}}],\"singleVisual\":{\"visualType\":\"multiRowCard\",\"projections\":{\"Values\":[{\"queryRef\":\"Sum(RLTR_DATA.Price Per Acre)\"}]},\"prototypeQuery\":{\"Version\":2,\"From\":[{\"Name\":\"r\",\"Entity\":\"RLTR_DATA\",\"Type\":0}],\"Select\":[{\"Aggregation\":{\"Expression\":{\"Column\":{\"Expression\":{\"SourceRef\":{\"Source\":\"r\"}},\"Property\":\"Price Per Acre\"}},\"Function\":1},\"Name\":\"Sum(RLTR_DATA.Price Per Acre)\",\"NativeReferenceName\":\"Average Price Per Acre\"}],\"OrderBy\":[{\"Direction\":2,\"Expression\":{\"Aggregation\":{\"Expression\":{\"Column\":{\"Expression\":{\"SourceRef\":{\"Source\":\"r\"}},\"Property\":\"Price Per Acre\"}},\"Function\":1}}}]},\"columnProperties\":{\"Sum(RLTR_DATA.Price Per Acre)\":{\"displayName\":\"Average Price Per Acre\"}},\"drillFilterOtherVisuals\":true,\"hasDefaultSort\":true,\"objects\":{\"categoryLabels\":[{\"properties\":{\"show\":{\"expr\":{\"Literal\":{\"Value\":\"true\"}}}}}]},\"vcObjects\":{\"title\":[{\"properties\":{\"show\":{\"expr\":{\"Literal\":{\"Value\":\"false\"}}},\"text\":{\"expr\":{\"Literal\":{\"Value\":\"'Average Price'\"}}}}}],\"background\":[{\"properties\":{\"show\":{\"expr\":{\"Literal\":{\"Value\":\"false\"}}}}}]}}}",
          "filters": "[]",
          "height": 52.83,
          "width": 199.66,
          "x": 0.00,
          "y": 526.48,
          "z": 7000.00
        },
        {
          "config": "{\"name\":\"291ba69462b1d157a778\",\"layouts\":[{\"id\":0,\"position\":{\"x\":0,\"y\":392.5597269624573,\"z\":6000,\"width\":199.65870307167236,\"height\":52.83276450511946,\"tabOrder\":6000}}],\"singleVisual\":{\"visualType\":\"multiRowCard\",\"projections\":{\"Values\":[{\"queryRef\":\"Sum(RLTR_DATA.PRICE)\"}]},\"prototypeQuery\":{\"Version\":2,\"From\":[{\"Name\":\"r\",\"Entity\":\"RLTR_DATA\",\"Type\":0}],\"Select\":[{\"Aggregation\":{\"Expression\":{\"Column\":{\"Expression\":{\"SourceRef\":{\"Source\":\"r\"}},\"Property\":\"Price\"}},\"Function\":3},\"Name\":\"Sum(RLTR_DATA.PRICE)\",\"NativeReferenceName\":\"Lowest List Price\"}],\"OrderBy\":[{\"Direction\":2,\"Expression\":{\"Aggregation\":{\"Expression\":{\"Column\":{\"Expression\":{\"SourceRef\":{\"Source\":\"r\"}},\"Property\":\"Price\"}},\"Function\":3}}}]},\"columnProperties\":{\"Sum(RLTR_DATA.PRICE)\":{\"displayName\":\"Lowest List Price\"}},\"drillFilterOtherVisuals\":true,\"hasDefaultSort\":true,\"objects\":{\"categoryLabels\":[{\"properties\":{\"show\":{\"expr\":{\"Literal\":{\"Value\":\"true\"}}}}}]},\"vcObjects\":{\"title\":[{\"properties\":{\"show\":{\"expr\":{\"Literal\":{\"Value\":\"false\"}}},\"text\":{\"expr\":{\"Literal\":{\"Value\":\"'Average Price'\"}}}}}],\"background\":[{\"properties\":{\"show\":{\"expr\":{\"Literal\":{\"Value\":\"false\"}}}}}]}}}",
          "filters": "[{\"name\":\"6f67782e938798fe5721\",\"expression\":{\"Column\":{\"Expression\":{\"SourceRef\":{\"Entity\":\"RLTR_DATA\"}},\"Property\":\"Price\"}},\"filter\":{\"Version\":2,\"From\":[{\"Name\":\"r\",\"Entity\":\"RLTR_DATA\",\"Type\":0}],\"Where\":[{\"Condition\":{\"Not\":{\"Expression\":{\"In\":{\"Expressions\":[{\"Column\":{\"Expression\":{\"SourceRef\":{\"Source\":\"r\"}},\"Property\":\"Price\"}}],\"Values\":[[{\"Literal\":{\"Value\":\"0D\"}}],[{\"Literal\":{\"Value\":\"1D\"}}]]}}}}}]},\"type\":\"Categorical\",\"howCreated\":1,\"objects\":{\"general\":[{\"properties\":{\"isInvertedSelectionMode\":{\"expr\":{\"Literal\":{\"Value\":\"true\"}}}}}]}}]",
          "height": 52.83,
          "width": 199.66,
          "x": 0.00,
          "y": 392.56,
          "z": 6000.00
        },
        {
          "config": "{\"name\":\"37265e299b63a04ac612\",\"layouts\":[{\"id\":0,\"position\":{\"x\":199.65870307167236,\"y\":128.39590443686006,\"z\":10000,\"width\":629.0784982935154,\"height\":591.6040955631399,\"tabOrder\":10000}}],\"singleVisual\":{\"visualType\":\"filledMap\",\"projections\":{\"Category\":[{\"queryRef\":\"RLTR_DATA.Location\",\"active\":true}],\"Series\":[{\"queryRef\":\"RLTR_DATA.County\"}],\"Tooltips\":[{\"queryRef\":\"Count(RLTR_DATA.UID)\"},{\"queryRef\":\"Sum(RLTR_DATA.Acres)\"},{\"queryRef\":\"Avg(RLTR_DATA.Price)\"},{\"queryRef\":\"Avg(RLTR_DATA.Price Per Acre)\"}]},\"prototypeQuery\":{\"Version\":2,\"From\":[{\"Name\":\"r\",\"Entity\":\"RLTR_DATA\",\"Type\":0}],\"Select\":[{\"Column\":{\"Expression\":{\"SourceRef\":{\"Source\":\"r\"}},\"Property\":\"Location\"},\"Name\":\"RLTR_DATA.Location\",\"NativeReferenceName\":\"Location\"},{\"Column\":{\"Expression\":{\"SourceRef\":{\"Source\":\"r\"}},\"Property\":\"County\"},\"Name\":\"RLTR_DATA.County\",\"NativeReferenceName\":\"County\"},{\"Aggregation\":{\"Expression\":{\"Column\":{\"Expression\":{\"SourceRef\":{\"Source\":\"r\"}},\"Property\":\"UID\"}},\"Function\":2},\"Name\":\"Count(RLTR_DATA.UID)\",\"NativeReferenceName\":\"# of Listings\"},{\"Aggregation\":{\"Expression\":{\"Column\":{\"Expression\":{\"SourceRef\":{\"Source\":\"r\"}},\"Property\":\"Price\"}},\"Function\":1},\"Name\":\"Avg(RLTR_DATA.Price)\",\"NativeReferenceName\":\"Average List Price\"},{\"Aggregation\":{\"Expression\":{\"Column\":{\"Expression\":{\"SourceRef\":{\"Source\":\"r\"}},\"Property\":\"Price Per Acre\"}},\"Function\":1},\"Name\":\"Avg(RLTR_DATA.Price Per Acre)\",\"NativeReferenceName\":\"Average Price Per Acre\"},{\"Aggregation\":{\"Expression\":{\"Column\":{\"Expression\":{\"SourceRef\":{\"Source\":\"r\"}},\"Property\":\"Acres\"}},\"Function\":1},\"Name\":\"Sum(RLTR_DATA.Acres)\",\"NativeReferenceName\":\"Average Acreage\"}]},\"columnProperties\":{\"CountNonNull(RLTR_DATA.UID)\":{\"displayName\":\"# of Listed Properties\"},\"Count(RLTR_DATA.UID)\":{\"displayName\":\"# of Listings\"},\"Avg(RLTR_DATA.Price)\":{\"displayName\":\"Average List Price\"},\"Avg(RLTR_DATA.Price Per Acre)\":{\"displayName\":\"Average Price Per Acre\"},\"Sum(RLTR_DATA.Acres)\":{\"displayName\":\"Average Acreage\"}},\"drillFilterOtherVisuals\":true,\"objects\":{\"mapStyles\":[{\"properties\":{\"mapTheme\":{\"expr\":{\"Literal\":{\"Value\":\"'grayscale'\"}}}}}],\"mapControls\":[{\"properties\":{\"showZoomButtons\":{\"expr\":{\"Literal\":{\"Value\":\"true\"}}},\"showLassoButton\":{\"expr\":{\"Literal\":{\"Value\":\"false\"}}}}}],\"legend\":[{\"properties\":{\"show\":{\"expr\":{\"Literal\":{\"Value\":\"false\"}}}}}],\"dataPoint\":[{\"properties\":{\"fillRule\":{\"linearGradient2\":{\"min\":{\"color\":{\"expr\":{\"Literal\":{\"Value\":\"'minColor'\"}}}},\"max\":{\"color\":{\"expr\":{\"Literal\":{\"Value\":\"'maxColor'\"}}}},\"nullColoringStrategy\":{\"strategy\":{\"expr\":{\"Literal\":{\"Value\":\"'asZero'\"}}}}}}}}],\"categoryLabels\":[{\"properties\":{\"show\":{\"expr\":{\"Literal\":{\"Value\":\"false\"}}}}}]},\"vcObjects\":{\"title\":[{\"properties\":{\"show\":{\"expr\":{\"Literal\":{\"Value\":\"false\"}}}}}],\"visualTooltip\":[{\"properties\":{\"transparency\":{\"expr\":{\"Literal\":{\"Value\":\"24D\"}}},\"themedBackground\":{\"solid\":{\"color\":{\"expr\":{\"ThemeDataColor\":{\"ColorId\":1,\"Percent\":0}}}}},\"themedTitleFontColor\":{\"solid\":{\"color\":{\"expr\":{\"ThemeDataColor\":{\"ColorId\":0,\"Percent\":0}}}}},\"themedValueFontColor\":{\"solid\":{\"color\":{\"expr\":{\"ThemeDataColor\":{\"ColorId\":0,\"Percent\":0}}}}},\"actionFontColor\":{\"solid\":{\"color\":{\"expr\":{\"ThemeDataColor\":{\"ColorId\":0,\"Percent\":0}}}}}}}]}}}",
          "filters": "[]",
          "height": 591.60,
          "width": 629.08,
          "x": 199.66,
          "y": 128.40,
          "z": 10000.00
        },
        {
          "config": "{\"name\":\"4db8eadbd4b0b4b96270\",\"layouts\":[{\"id\":0,\"position\":{\"x\":2.4573378839590445,\"y\":239.59044368600684,\"z\":17000,\"width\":194.74402730375428,\"height\":33.1740614334471,\"tabOrder\":17000}}],\"singleVisual\":{\"visualType\":\"shape\",\"drillFilterOtherVisuals\":true,\"objects\":{\"shape\":[{\"properties\":{\"tileShape\":{\"expr\":{\"Literal\":{\"Value\":\"'line'\"}}}}}],\"rotation\":[{\"properties\":{\"shapeAngle\":{\"expr\":{\"Literal\":{\"Value\":\"0L\"}}}}}],\"fill\":[{\"properties\":{\"fillColor\":{\"solid\":{\"color\":{\"expr\":{\"ThemeDataColor\":{\"ColorId\":0,\"Percent\":-0.1}}}}}},\"selector\":{\"id\":\"default\"}}],\"outline\":[{\"properties\":{\"show\":{\"expr\":{\"Literal\":{\"Value\":\"true\"}}}}},{\"properties\":{\"lineColor\":{\"solid\":{\"color\":{\"expr\":{\"ThemeDataColor\":{\"ColorId\":0,\"Percent\":-0.1}}}}}},\"selector\":{\"id\":\"default\"}}]}},\"howCreated\":\"InsertVisualButton\"}",
          "filters": "[]",
          "height": 33.17,
          "width": 194.74,
          "x": 2.46,
          "y": 239.59,
          "z": 17000.00
        },
        {
          "config": "{\"name\":\"73a642f971de0cff307d\",\"layouts\":[{\"id\":0,\"position\":{\"x\":0,\"y\":632.1501706484642,\"z\":9000,\"width\":199.65870307167236,\"height\":52.83276450511946,\"tabOrder\":9000}}],\"singleVisual\":{\"visualType\":\"multiRowCard\",\"projections\":{\"Values\":[{\"queryRef\":\"Sum(RLTR_DATA.Price Per Acre)\"}]},\"prototypeQuery\":{\"Version\":2,\"From\":[{\"Name\":\"r\",\"Entity\":\"RLTR_DATA\",\"Type\":0}],\"Select\":[{\"Aggregation\":{\"Expression\":{\"Column\":{\"Expression\":{\"SourceRef\":{\"Source\":\"r\"}},\"Property\":\"Price Per Acre\"}},\"Function\":3},\"Name\":\"Sum(RLTR_DATA.Price Per Acre)\",\"NativeReferenceName\":\"Min of Price Per Acre\"}],\"OrderBy\":[{\"Direction\":2,\"Expression\":{\"Aggregation\":{\"Expression\":{\"Column\":{\"Expression\":{\"SourceRef\":{\"Source\":\"r\"}},\"Property\":\"Price Per Acre\"}},\"Function\":3}}}]},\"columnProperties\":{\"Sum(RLTR_DATA.Price Per Acre)\":{\"displayName\":\"Lowest Price Per Acre\"}},\"drillFilterOtherVisuals\":true,\"hasDefaultSort\":true,\"objects\":{\"categoryLabels\":[{\"properties\":{\"show\":{\"expr\":{\"Literal\":{\"Value\":\"true\"}}}}}]},\"vcObjects\":{\"title\":[{\"properties\":{\"show\":{\"expr\":{\"Literal\":{\"Value\":\"false\"}}},\"text\":{\"expr\":{\"Literal\":{\"Value\":\"'Average Price'\"}}}}}],\"background\":[{\"properties\":{\"show\":{\"expr\":{\"Literal\":{\"Value\":\"false\"}}}}}]}}}",
          "filters": "[{\"name\":\"6f67782e938798fe5721\",\"expression\":{\"Column\":{\"Expression\":{\"SourceRef\":{\"Entity\":\"RLTR_DATA\"}},\"Property\":\"Price\"}},\"filter\":{\"Version\":2,\"From\":[{\"Name\":\"r\",\"Entity\":\"RLTR_DATA\",\"Type\":0}],\"Where\":[{\"Condition\":{\"Not\":{\"Expression\":{\"In\":{\"Expressions\":[{\"Column\":{\"Expression\":{\"SourceRef\":{\"Source\":\"r\"}},\"Property\":\"Price\"}}],\"Values\":[[{\"Literal\":{\"Value\":\"0D\"}}],[{\"Literal\":{\"Value\":\"1D\"}}]]}}}}}]},\"type\":\"Categorical\",\"howCreated\":1,\"objects\":{\"general\":[{\"properties\":{\"isInvertedSelectionMode\":{\"expr\":{\"Literal\":{\"Value\":\"true\"}}}}}]}}]",
          "height": 52.83,
          "width": 199.66,
          "x": 0.00,
          "y": 632.15,
          "z": 9000.00
        },
        {
          "config": "{\"name\":\"7e422f0a109c91b6d092\",\"layouts\":[{\"id\":0,\"position\":{\"x\":828.7372013651877,\"y\":409.76109215017067,\"z\":14000,\"width\":451.5358361774744,\"height\":151.740614334471,\"tabOrder\":14000}}],\"singleVisual\":{\"visualType\":\"funnel\",\"projections\":{\"Category\":[{\"queryRef\":\"RLTR_DATA.County\",\"active\":true}],\"Y\":[{\"queryRef\":\"Sum(RLTR_DATA.Price)\"}]},\"prototypeQuery\":{\"Version\":2,\"From\":[{\"Name\":\"r\",\"Entity\":\"RLTR_DATA\",\"Type\":0}],\"Select\":[{\"Column\":{\"Expression\":{\"SourceRef\":{\"Source\":\"r\"}},\"Property\":\"County\"},\"Name\":\"RLTR_DATA.County\",\"NativeReferenceName\":\"County\"},{\"Aggregation\":{\"Expression\":{\"Column\":{\"Expression\":{\"SourceRef\":{\"Source\":\"r\"}},\"Property\":\"Price\"}},\"Function\":1},\"Name\":\"Sum(RLTR_DATA.Price)\",\"NativeReferenceName\":\"Average of Price\"}],\"OrderBy\":[{\"Direction\":2,\"Expression\":{\"Aggregation\":{\"Expression\":{\"Column\":{\"Expression\":{\"SourceRef\":{\"Source\":\"r\"}},\"Property\":\"Price\"}},\"Function\":1}}}]},\"drillFilterOtherVisuals\":true,\"hasDefaultSort\":true,\"objects\":{\"dataPoint\":[{\"properties\":{\"fill\":{\"solid\":{\"color\":{\"expr\":{\"ThemeDataColor\":{\"ColorId\":2,\"Percent\":0.6}}}}}}}],\"percentBarLabel\":[{\"properties\":{\"show\":{\"expr\":{\"Literal\":{\"Value\":\"false\"}}}}}]},\"vcObjects\":{\"title\":[{\"properties\":{\"text\":{\"expr\":{\"Literal\":{\"Value\":\"'Top 5 Counties with Lowest List Price'\"}}},\"alignment\":{\"expr\":{\"Literal\":{\"Value\":\"'center'\"}}},\"fontSize\":{\"expr\":{\"Literal\":{\"Value\":\"12D\"}}}}}],\"background\":[{\"properties\":{\"show\":{\"expr\":{\"Literal\":{\"Value\":\"false\"}}}}}],\"visualTooltip\":[{\"properties\":{\"themedTitleFontColor\":{\"solid\":{\"color\":{\"expr\":{\"ThemeDataColor\":{\"ColorId\":0,\"Percent\":0}}}}},\"themedValueFontColor\":{\"solid\":{\"color\":{\"expr\":{\"ThemeDataColor\":{\"ColorId\":0,\"Percent\":0}}}}},\"actionFontColor\":{\"solid\":{\"color\":{\"expr\":{\"ThemeDataColor\":{\"ColorId\":0,\"Percent\":0}}}}},\"themedBackground\":{\"solid\":{\"color\":{\"expr\":{\"ThemeDataColor\":{\"ColorId\":1,\"Percent\":0}}}}},\"transparency\":{\"expr\":{\"Literal\":{\"Value\":\"25D\"}}}}}]}}}",
          "filters": "[{\"expression\":{\"Column\":{\"Expression\":{\"SourceRef\":{\"Entity\":\"RLTR_DATA\"}},\"Property\":\"County\"}},\"filter\":{\"Version\":2,\"From\":[{\"Name\":\"subquery\",\"Expression\":{\"Subquery\":{\"Query\":{\"Version\":2,\"From\":[{\"Name\":\"r\",\"Entity\":\"RLTR_DATA\",\"Type\":0}],\"Select\":[{\"Column\":{\"Expression\":{\"SourceRef\":{\"Source\":\"r\"}},\"Property\":\"County\"},\"Name\":\"field\"}],\"OrderBy\":[{\"Direction\":1,\"Expression\":{\"Aggregation\":{\"Expression\":{\"Column\":{\"Expression\":{\"SourceRef\":{\"Source\":\"r\"}},\"Property\":\"Price Per Acre\"}},\"Function\":1}}}],\"Top\":5}}},\"Type\":2},{\"Name\":\"r\",\"Entity\":\"RLTR_DATA\",\"Type\":0}],\"Where\":[{\"Condition\":{\"In\":{\"Expressions\":[{\"Column\":{\"Expression\":{\"SourceRef\":{\"Source\":\"r\"}},\"Property\":\"County\"}}],\"Table\":{\"SourceRef\":{\"Source\":\"subquery\"}}}}}]},\"type\":\"TopN\",\"howCreated\":0,\"isHiddenInViewMode\":false},{\"name\":\"445c449cefc61245d952\",\"expression\":{\"Column\":{\"Expression\":{\"SourceRef\":{\"Entity\":\"RLTR_DATA\"}},\"Property\":\"Price\"}},\"filter\":{\"Version\":2,\"From\":[{\"Name\":\"r\",\"Entity\":\"RLTR_DATA\",\"Type\":0}],\"Where\":[{\"Condition\":{\"Comparison\":{\"ComparisonKind\":1,\"Left\":{\"Column\":{\"Expression\":{\"SourceRef\":{\"Source\":\"r\"}},\"Property\":\"Price\"}},\"Right\":{\"Literal\":{\"Value\":\"1L\"}}}}}]},\"type\":\"Advanced\",\"howCreated\":1}]",
          "height": 151.74,
          "width": 451.54,
          "x": 828.74,
          "y": 409.76,
          "z": 14000.00
        },
        {
          "config": "{\"name\":\"85a2356daa3480e4bc35\",\"layouts\":[{\"id\":0,\"position\":{\"x\":977.9381443298969,\"y\":19.175257731958762,\"z\":4000,\"width\":301.8556701030928,\"height\":100.20618556701031,\"tabOrder\":4000}}],\"singleVisual\":{\"visualType\":\"slicer\",\"projections\":{\"Values\":[{\"queryRef\":\"RLTR_DATA.Price Per Acre\",\"active\":true}]},\"prototypeQuery\":{\"Version\":2,\"From\":[{\"Name\":\"r\",\"Entity\":\"RLTR_DATA\",\"Type\":0}],\"Select\":[{\"Column\":{\"Expression\":{\"SourceRef\":{\"Source\":\"r\"}},\"Property\":\"Price Per Acre\"},\"Name\":\"RLTR_DATA.Price Per Acre\",\"NativeReferenceName\":\"Price Per Acre\"}]},\"drillFilterOtherVisuals\":true,\"objects\":{\"data\":[{\"properties\":{\"mode\":{\"expr\":{\"Literal\":{\"Value\":\"'Between'\"}}}}}],\"general\":[{\"properties\":{\"selfFilterEnabled\":{\"expr\":{\"Literal\":{\"Value\":\"true\"}}}}}],\"header\":[{\"properties\":{\"show\":{\"expr\":{\"Literal\":{\"Value\":\"false\"}}}}}],\"numericInputStyle\":[{\"properties\":{\"textSize\":{\"expr\":{\"Literal\":{\"Value\":\"8D\"}}}}}],\"slider\":[{\"properties\":{\"color\":{\"solid\":{\"color\":{\"expr\":{\"ThemeDataColor\":{\"ColorId\":1,\"Percent\":0}}}}}}}]},\"vcObjects\":{\"title\":[{\"properties\":{\"show\":{\"expr\":{\"Literal\":{\"Value\":\"true\"}}},\"text\":{\"expr\":{\"Literal\":{\"Value\":\"'Price Per Acre'\"}}},\"alignment\":{\"expr\":{\"Literal\":{\"Value\":\"'center'\"}}},\"fontSize\":{\"expr\":{\"Literal\":{\"Value\":\"10D\"}}}}}],\"background\":[{\"properties\":{\"show\":{\"expr\":{\"Literal\":{\"Value\":\"false\"}}}}}]}}}",
          "filters": "[{\"name\":\"5ce0f1c44cda63fba84d\",\"expression\":{\"Column\":{\"Expression\":{\"SourceRef\":{\"Entity\":\"RLTR_DATA\"}},\"Property\":\"County\"}},\"filter\":{\"Version\":2,\"From\":[{\"Name\":\"r\",\"Entity\":\"RLTR_DATA\",\"Type\":0}],\"Where\":[{\"Condition\":{\"Not\":{\"Expression\":{\"In\":{\"Expressions\":[{\"Column\":{\"Expression\":{\"SourceRef\":{\"Source\":\"r\"}},\"Property\":\"County\"}}],\"Values\":[[{\"Literal\":{\"Value\":\"null\"}}]]}}}}}]},\"type\":\"Categorical\",\"howCreated\":1,\"objects\":{\"general\":[{\"properties\":{\"isInvertedSelectionMode\":{\"expr\":{\"Literal\":{\"Value\":\"true\"}}}}}]},\"isHiddenInViewMode\":false}]",
          "height": 100.21,
          "width": 301.86,
          "x": 977.94,
          "y": 19.18,
          "z": 4000.00
        },
        {
          "config": "{\"name\":\"935bf9c0f1b046babf3b\",\"layouts\":[{\"id\":0,\"position\":{\"x\":321.64948453608247,\"y\":19.175257731958762,\"z\":2000,\"width\":301.2371134020618,\"height\":100.20618556701031,\"tabOrder\":2000}}],\"singleVisual\":{\"visualType\":\"slicer\",\"projections\":{\"Values\":[{\"queryRef\":\"RLTR_DATA.Acres\",\"active\":true}]},\"prototypeQuery\":{\"Version\":2,\"From\":[{\"Name\":\"r\",\"Entity\":\"RLTR_DATA\",\"Type\":0}],\"Select\":[{\"Column\":{\"Expression\":{\"SourceRef\":{\"Source\":\"r\"}},\"Property\":\"Acres\"},\"Name\":\"RLTR_DATA.Acres\",\"NativeReferenceName\":\"Acres\"}]},\"drillFilterOtherVisuals\":true,\"objects\":{\"data\":[{\"properties\":{\"mode\":{\"expr\":{\"Literal\":{\"Value\":\"'Between'\"}}}}}],\"general\":[{\"properties\":{\"selfFilterEnabled\":{\"expr\":{\"Literal\":{\"Value\":\"true\"}}}}}],\"header\":[{\"properties\":{\"show\":{\"expr\":{\"Literal\":{\"Value\":\"false\"}}}}}],\"numericInputStyle\":[{\"properties\":{\"textSize\":{\"expr\":{\"Literal\":{\"Value\":\"8D\"}}}}}],\"slider\":[{\"properties\":{\"color\":{\"solid\":{\"color\":{\"expr\":{\"ThemeDataColor\":{\"ColorId\":1,\"Percent\":0}}}}}}}]},\"vcObjects\":{\"title\":[{\"properties\":{\"show\":{\"expr\":{\"Literal\":{\"Value\":\"true\"}}},\"text\":{\"expr\":{\"Literal\":{\"Value\":\"'Number of Acres'\"}}},\"alignment\":{\"expr\":{\"Literal\":{\"Value\":\"'center'\"}}},\"fontSize\":{\"expr\":{\"Literal\":{\"Value\":\"10D\"}}}}}],\"background\":[{\"properties\":{\"show\":{\"expr\":{\"Literal\":{\"Value\":\"false\"}}}}}]}}}",
          "filters": "[{\"name\":\"5ce0f1c44cda63fba84d\",\"expression\":{\"Column\":{\"Expression\":{\"SourceRef\":{\"Entity\":\"RLTR_DATA\"}},\"Property\":\"County\"}},\"filter\":{\"Version\":2,\"From\":[{\"Name\":\"r\",\"Entity\":\"RLTR_DATA\",\"Type\":0}],\"Where\":[{\"Condition\":{\"Not\":{\"Expression\":{\"In\":{\"Expressions\":[{\"Column\":{\"Expression\":{\"SourceRef\":{\"Source\":\"r\"}},\"Property\":\"County\"}}],\"Values\":[[{\"Literal\":{\"Value\":\"null\"}}]]}}}}}]},\"type\":\"Categorical\",\"howCreated\":1,\"objects\":{\"general\":[{\"properties\":{\"isInvertedSelectionMode\":{\"expr\":{\"Literal\":{\"Value\":\"true\"}}}}}]},\"isHiddenInViewMode\":false}]",
          "height": 100.21,
          "width": 301.24,
          "x": 321.65,
          "y": 19.18,
          "z": 2000.00
        },
        {
          "config": "{\"name\":\"972af63a2cbd00b1f810\",\"layouts\":[{\"id\":0,\"position\":{\"x\":828.7372013651877,\"y\":568.2593856655291,\"z\":13000,\"width\":451.5358361774744,\"height\":151.740614334471,\"tabOrder\":13000}}],\"singleVisual\":{\"visualType\":\"funnel\",\"projections\":{\"Category\":[{\"queryRef\":\"RLTR_DATA.County\",\"active\":true}],\"Y\":[{\"queryRef\":\"Sum(RLTR_DATA.Price Per Acre)\"}]},\"prototypeQuery\":{\"Version\":2,\"From\":[{\"Name\":\"r\",\"Entity\":\"RLTR_DATA\",\"Type\":0}],\"Select\":[{\"Column\":{\"Expression\":{\"SourceRef\":{\"Source\":\"r\"}},\"Property\":\"County\"},\"Name\":\"RLTR_DATA.County\",\"NativeReferenceName\":\"County\"},{\"Aggregation\":{\"Expression\":{\"Column\":{\"Expression\":{\"SourceRef\":{\"Source\":\"r\"}},\"Property\":\"Price Per Acre\"}},\"Function\":1},\"Name\":\"Sum(RLTR_DATA.Price Per Acre)\",\"NativeReferenceName\":\"Average of Price Per Acre\"}],\"OrderBy\":[{\"Direction\":2,\"Expression\":{\"Aggregation\":{\"Expression\":{\"Column\":{\"Expression\":{\"SourceRef\":{\"Source\":\"r\"}},\"Property\":\"Price Per Acre\"}},\"Function\":1}}}]},\"drillFilterOtherVisuals\":true,\"hasDefaultSort\":true,\"objects\":{\"dataPoint\":[{\"properties\":{\"fill\":{\"solid\":{\"color\":{\"expr\":{\"ThemeDataColor\":{\"ColorId\":2,\"Percent\":0.6}}}}}}}],\"percentBarLabel\":[{\"properties\":{\"show\":{\"expr\":{\"Literal\":{\"Value\":\"false\"}}}}}]},\"vcObjects\":{\"title\":[{\"properties\":{\"text\":{\"expr\":{\"Literal\":{\"Value\":\"'Top 5 Counties with Lowest Price Per Acre'\"}}},\"alignment\":{\"expr\":{\"Literal\":{\"Value\":\"'center'\"}}},\"fontSize\":{\"expr\":{\"Literal\":{\"Value\":\"12D\"}}}}}],\"background\":[{\"properties\":{\"show\":{\"expr\":{\"Literal\":{\"Value\":\"false\"}}}}}],\"visualTooltip\":[{\"properties\":{\"themedTitleFontColor\":{\"solid\":{\"color\":{\"expr\":{\"ThemeDataColor\":{\"ColorId\":0,\"Percent\":0}}}}},\"themedValueFontColor\":{\"solid\":{\"color\":{\"expr\":{\"ThemeDataColor\":{\"ColorId\":0,\"Percent\":0}}}}},\"actionFontColor\":{\"solid\":{\"color\":{\"expr\":{\"ThemeDataColor\":{\"ColorId\":0,\"Percent\":0}}}}},\"themedBackground\":{\"solid\":{\"color\":{\"expr\":{\"ThemeDataColor\":{\"ColorId\":1,\"Percent\":0}}}}},\"transparency\":{\"expr\":{\"Literal\":{\"Value\":\"25D\"}}}}}]}}}",
          "filters": "[{\"expression\":{\"Column\":{\"Expression\":{\"SourceRef\":{\"Entity\":\"RLTR_DATA\"}},\"Property\":\"County\"}},\"filter\":{\"Version\":2,\"From\":[{\"Name\":\"subquery\",\"Expression\":{\"Subquery\":{\"Query\":{\"Version\":2,\"From\":[{\"Name\":\"r\",\"Entity\":\"RLTR_DATA\",\"Type\":0}],\"Select\":[{\"Column\":{\"Expression\":{\"SourceRef\":{\"Source\":\"r\"}},\"Property\":\"County\"},\"Name\":\"field\"}],\"OrderBy\":[{\"Direction\":1,\"Expression\":{\"Aggregation\":{\"Expression\":{\"Column\":{\"Expression\":{\"SourceRef\":{\"Source\":\"r\"}},\"Property\":\"Price Per Acre\"}},\"Function\":1}}}],\"Top\":5}}},\"Type\":2},{\"Name\":\"r\",\"Entity\":\"RLTR_DATA\",\"Type\":0}],\"Where\":[{\"Condition\":{\"In\":{\"Expressions\":[{\"Column\":{\"Expression\":{\"SourceRef\":{\"Source\":\"r\"}},\"Property\":\"County\"}}],\"Table\":{\"SourceRef\":{\"Source\":\"subquery\"}}}}}]},\"type\":\"TopN\",\"howCreated\":0,\"isHiddenInViewMode\":false},{\"name\":\"445c449cefc61245d952\",\"expression\":{\"Column\":{\"Expression\":{\"SourceRef\":{\"Entity\":\"RLTR_DATA\"}},\"Property\":\"Price\"}},\"filter\":{\"Version\":2,\"From\":[{\"Name\":\"r\",\"Entity\":\"RLTR_DATA\",\"Type\":0}],\"Where\":[{\"Condition\":{\"Comparison\":{\"ComparisonKind\":1,\"Left\":{\"Column\":{\"Expression\":{\"SourceRef\":{\"Source\":\"r\"}},\"Property\":\"Price\"}},\"Right\":{\"Literal\":{\"Value\":\"1L\"}}}}}]},\"type\":\"Advanced\",\"howCreated\":1}]",
          "height": 151.74,
          "width": 451.54,
          "x": 828.74,
          "y": 568.26,
          "z": 13000.00
        },
        {
          "config": "{\"name\":\"b954cddda987d8bd16fb\",\"layouts\":[{\"id\":0,\"position\":{\"x\":648.2474226804123,\"y\":23.505154639175256,\"z\":3000,\"width\":301.8556701030928,\"height\":100.20618556701031,\"tabOrder\":3000}}],\"singleVisual\":{\"visualType\":\"slicer\",\"projections\":{\"Values\":[{\"queryRef\":\"RLTR_DATA.Price\",\"active\":true}]},\"prototypeQuery\":{\"Version\":2,\"From\":[{\"Name\":\"r\",\"Entity\":\"RLTR_DATA\",\"Type\":0}],\"Select\":[{\"Column\":{\"Expression\":{\"SourceRef\":{\"Source\":\"r\"}},\"Property\":\"Price\"},\"Name\":\"RLTR_DATA.Price\",\"NativeReferenceName\":\"Price\"}]},\"drillFilterOtherVisuals\":true,\"objects\":{\"data\":[{\"properties\":{\"numericEnd\":{\"expr\":{\"Literal\":{\"Value\":\"5D\"}}},\"mode\":{\"expr\":{\"Literal\":{\"Value\":\"'Between'\"}}}}}],\"general\":[{\"properties\":{\"selfFilterEnabled\":{\"expr\":{\"Literal\":{\"Value\":\"true\"}}}}}],\"header\":[{\"properties\":{\"show\":{\"expr\":{\"Literal\":{\"Value\":\"false\"}}}}}],\"numericInputStyle\":[{\"properties\":{\"textSize\":{\"expr\":{\"Literal\":{\"Value\":\"8D\"}}}}}],\"slider\":[{\"properties\":{\"color\":{\"solid\":{\"color\":{\"expr\":{\"ThemeDataColor\":{\"ColorId\":1,\"Percent\":0}}}}}}}]},\"vcObjects\":{\"title\":[{\"properties\":{\"show\":{\"expr\":{\"Literal\":{\"Value\":\"true\"}}},\"text\":{\"expr\":{\"Literal\":{\"Value\":\"'Listed Price'\"}}},\"alignment\":{\"expr\":{\"Literal\":{\"Value\":\"'center'\"}}},\"fontSize\":{\"expr\":{\"Literal\":{\"Value\":\"10D\"}}}}}],\"background\":[{\"properties\":{\"show\":{\"expr\":{\"Literal\":{\"Value\":\"false\"}}}}}]}}}",
          "filters": "[{\"name\":\"5ce0f1c44cda63fba84d\",\"expression\":{\"Column\":{\"Expression\":{\"SourceRef\":{\"Entity\":\"RLTR_DATA\"}},\"Property\":\"County\"}},\"filter\":{\"Version\":2,\"From\":[{\"Name\":\"r\",\"Entity\":\"RLTR_DATA\",\"Type\":0}],\"Where\":[{\"Condition\":{\"Not\":{\"Expression\":{\"In\":{\"Expressions\":[{\"Column\":{\"Expression\":{\"SourceRef\":{\"Source\":\"r\"}},\"Property\":\"County\"}}],\"Values\":[[{\"Literal\":{\"Value\":\"null\"}}]]}}}}}]},\"type\":\"Categorical\",\"howCreated\":1,\"objects\":{\"general\":[{\"properties\":{\"isInvertedSelectionMode\":{\"expr\":{\"Literal\":{\"Value\":\"true\"}}}}}]},\"isHiddenInViewMode\":false}]",
          "height": 100.21,
          "width": 301.86,
          "x": 648.25,
          "y": 23.51,
          "z": 3000.00
        },
        {
          "config": "{\"name\":\"c4eca28df03068822218\",\"layouts\":[{\"id\":0,\"position\":{\"x\":0,\"y\":181.22866894197952,\"z\":15000,\"width\":199.65870307167236,\"height\":52.83276450511946,\"tabOrder\":15000}}],\"singleVisual\":{\"visualType\":\"multiRowCard\",\"projections\":{\"Values\":[{\"queryRef\":\"Sum(RLTR_DATA.Time On Site)\"}]},\"prototypeQuery\":{\"Version\":2,\"From\":[{\"Name\":\"r\",\"Entity\":\"RLTR_DATA\",\"Type\":0}],\"Select\":[{\"Aggregation\":{\"Expression\":{\"Column\":{\"Expression\":{\"SourceRef\":{\"Source\":\"r\"}},\"Property\":\"Time On Site\"}},\"Function\":1},\"Name\":\"Sum(RLTR_DATA.Time On Site)\",\"NativeReferenceName\":\"Average of Days Listed\"}],\"OrderBy\":[{\"Direction\":2,\"Expression\":{\"Aggregation\":{\"Expression\":{\"Column\":{\"Expression\":{\"SourceRef\":{\"Source\":\"r\"}},\"Property\":\"Time On Site\"}},\"Function\":1}}}]},\"columnProperties\":{\"CountNonNull(RLTR_DATA.UID)\":{\"formatString\":null},\"Sum(RLTR_DATA.Time On Site)\":{\"displayName\":\"Average of Days Listed\"}},\"drillFilterOtherVisuals\":true,\"hasDefaultSort\":true,\"objects\":{\"categoryLabels\":[{\"properties\":{\"show\":{\"expr\":{\"Literal\":{\"Value\":\"true\"}}}}}]},\"vcObjects\":{\"title\":[{\"properties\":{\"show\":{\"expr\":{\"Literal\":{\"Value\":\"false\"}}},\"text\":{\"expr\":{\"Literal\":{\"Value\":\"'Average Price'\"}}}}}],\"background\":[{\"properties\":{\"show\":{\"expr\":{\"Literal\":{\"Value\":\"false\"}}}}}]}}}",
          "filters": "[]",
          "height": 52.83,
          "width": 199.66,
          "x": 0.00,
          "y": 181.23,
          "z": 15000.00
        },
        {
          "config": "{\"name\":\"c8cef30a1d40027bdc92\",\"layouts\":[{\"id\":0,\"position\":{\"x\":0,\"y\":579.3174061433447,\"z\":8000,\"width\":199.65870307167236,\"height\":52.83276450511946,\"tabOrder\":8000}}],\"singleVisual\":{\"visualType\":\"multiRowCard\",\"projections\":{\"Values\":[{\"queryRef\":\"Sum(RLTR_DATA.Price Per Acre)\"}]},\"prototypeQuery\":{\"Version\":2,\"From\":[{\"Name\":\"r\",\"Entity\":\"RLTR_DATA\",\"Type\":0}],\"Select\":[{\"Aggregation\":{\"Expression\":{\"Column\":{\"Expression\":{\"SourceRef\":{\"Source\":\"r\"}},\"Property\":\"Price Per Acre\"}},\"Function\":4},\"Name\":\"Sum(RLTR_DATA.Price Per Acre)\",\"NativeReferenceName\":\"Highest Price Per Acre\"}],\"OrderBy\":[{\"Direction\":2,\"Expression\":{\"Aggregation\":{\"Expression\":{\"Column\":{\"Expression\":{\"SourceRef\":{\"Source\":\"r\"}},\"Property\":\"Price Per Acre\"}},\"Function\":4}}}]},\"columnProperties\":{\"Sum(RLTR_DATA.Price Per Acre)\":{\"displayName\":\"Highest Price Per Acre\"}},\"drillFilterOtherVisuals\":true,\"hasDefaultSort\":true,\"objects\":{\"categoryLabels\":[{\"properties\":{\"show\":{\"expr\":{\"Literal\":{\"Value\":\"true\"}}}}}]},\"vcObjects\":{\"title\":[{\"properties\":{\"show\":{\"expr\":{\"Literal\":{\"Value\":\"false\"}}},\"text\":{\"expr\":{\"Literal\":{\"Value\":\"'Average Price'\"}}}}}],\"background\":[{\"properties\":{\"show\":{\"expr\":{\"Literal\":{\"Value\":\"false\"}}}}}]}}}",
          "filters": "[]",
          "height": 52.83,
          "width": 199.66,
          "x": 0.00,
          "y": 579.32,
          "z": 8000.00
        },
        {
          "config": "{\"name\":\"cf416eb4fd2224395989\",\"layouts\":[{\"id\":0,\"position\":{\"x\":0.7835891406134625,\"y\":6.185567010309278,\"z\":0,\"width\":301.6382252559727,\"height\":63.27645051194539,\"tabOrder\":0}}],\"singleVisual\":{\"visualType\":\"slicer\",\"projections\":{\"Values\":[{\"queryRef\":\"RLTR_DATA.County\",\"active\":true}]},\"prototypeQuery\":{\"Version\":2,\"From\":[{\"Name\":\"r\",\"Entity\":\"RLTR_DATA\",\"Type\":0}],\"Select\":[{\"Column\":{\"Expression\":{\"SourceRef\":{\"Source\":\"r\"}},\"Property\":\"County\"},\"Name\":\"RLTR_DATA.County\",\"NativeReferenceName\":\"County\"}]},\"drillFilterOtherVisuals\":true,\"objects\":{\"data\":[{\"properties\":{\"mode\":{\"expr\":{\"Literal\":{\"Value\":\"'Dropdown'\"}}}}}],\"general\":[{\"properties\":{\"selfFilterEnabled\":{\"expr\":{\"Literal\":{\"Value\":\"true\"}}}}}],\"header\":[{\"properties\":{\"show\":{\"expr\":{\"Literal\":{\"Value\":\"false\"}}}}}],\"items\":[{\"properties\":{\"textSize\":{\"expr\":{\"Literal\":{\"Value\":\"10D\"}}}}}]},\"vcObjects\":{\"title\":[{\"properties\":{\"show\":{\"expr\":{\"Literal\":{\"Value\":\"true\"}}},\"text\":{\"expr\":{\"Literal\":{\"Value\":\"'Select A County'\"}}},\"alignment\":{\"expr\":{\"Literal\":{\"Value\":\"'center'\"}}},\"fontSize\":{\"expr\":{\"Literal\":{\"Value\":\"10D\"}}}}}],\"background\":[{\"properties\":{\"show\":{\"expr\":{\"Literal\":{\"Value\":\"false\"}}}}}]}}}",
          "filters": "[{\"name\":\"5ce0f1c44cda63fba84d\",\"expression\":{\"Column\":{\"Expression\":{\"SourceRef\":{\"Entity\":\"RLTR_DATA\"}},\"Property\":\"County\"}},\"filter\":{\"Version\":2,\"From\":[{\"Name\":\"r\",\"Entity\":\"RLTR_DATA\",\"Type\":0}],\"Where\":[{\"Condition\":{\"Not\":{\"Expression\":{\"In\":{\"Expressions\":[{\"Column\":{\"Expression\":{\"SourceRef\":{\"Source\":\"r\"}},\"Property\":\"County\"}}],\"Values\":[[{\"Literal\":{\"Value\":\"null\"}}]]}}}}}]},\"type\":\"Categorical\",\"howCreated\":0,\"objects\":{\"general\":[{\"properties\":{\"isInvertedSelectionMode\":{\"expr\":{\"Literal\":{\"Value\":\"true\"}}}}}]},\"isHiddenInViewMode\":false}]",
          "height": 63.28,
          "width": 301.64,
          "x": 0.78,
          "y": 6.19,
          "z": 0.00
        },
        {
          "config": "{\"name\":\"e2633dff84fc995dc6eb\",\"layouts\":[{\"id\":0,\"position\":{\"x\":828.122866894198,\"y\":128.39590443686006,\"z\":16000,\"width\":452.15017064846415,\"height\":264.16382252559725,\"tabOrder\":16000}}],\"singleVisual\":{\"visualType\":\"pieChart\",\"projections\":{\"Category\":[{\"queryRef\":\"RLTR_DATA.Status\",\"active\":true}],\"Y\":[{\"queryRef\":\"Count(RLTR_DATA.UID)\"}],\"Tooltips\":[{\"queryRef\":\"Sum(RLTR_DATA.Acres)\"},{\"queryRef\":\"Sum(RLTR_DATA.Price)\"},{\"queryRef\":\"Sum(RLTR_DATA.Price Per Acre)\"}]},\"prototypeQuery\":{\"Version\":2,\"From\":[{\"Name\":\"r\",\"Entity\":\"RLTR_DATA\",\"Type\":0}],\"Select\":[{\"Column\":{\"Expression\":{\"SourceRef\":{\"Source\":\"r\"}},\"Property\":\"Status\"},\"Name\":\"RLTR_DATA.Status\",\"NativeReferenceName\":\"Property Type\"},{\"Aggregation\":{\"Expression\":{\"Column\":{\"Expression\":{\"SourceRef\":{\"Source\":\"r\"}},\"Property\":\"UID\"}},\"Function\":2},\"Name\":\"Count(RLTR_DATA.UID)\",\"NativeReferenceName\":\"# of Listings\"},{\"Aggregation\":{\"Expression\":{\"Column\":{\"Expression\":{\"SourceRef\":{\"Source\":\"r\"}},\"Property\":\"Price\"}},\"Function\":1},\"Name\":\"Sum(RLTR_DATA.Price)\",\"NativeReferenceName\":\"Average List Price\"},{\"Aggregation\":{\"Expression\":{\"Column\":{\"Expression\":{\"SourceRef\":{\"Source\":\"r\"}},\"Property\":\"Price Per Acre\"}},\"Function\":1},\"Name\":\"Sum(RLTR_DATA.Price Per Acre)\",\"NativeReferenceName\":\"Average of Price Per Acre\"},{\"Aggregation\":{\"Expression\":{\"Column\":{\"Expression\":{\"SourceRef\":{\"Source\":\"r\"}},\"Property\":\"Acres\"}},\"Function\":1},\"Name\":\"Sum(RLTR_DATA.Acres)\",\"NativeReferenceName\":\"Average Acreage\"}],\"OrderBy\":[{\"Direction\":2,\"Expression\":{\"Aggregation\":{\"Expression\":{\"Column\":{\"Expression\":{\"SourceRef\":{\"Source\":\"r\"}},\"Property\":\"UID\"}},\"Function\":2}}}]},\"columnProperties\":{\"RLTR_DATA.Status\":{\"displayName\":\"Property Type\"},\"Count(RLTR_DATA.UID)\":{\"displayName\":\"# of Listings\"},\"Sum(RLTR_DATA.Price)\":{\"displayName\":\"Average List Price\"},\"Sum(RLTR_DATA.Price Per Acre)\":{\"displayName\":\"Average Price Per Acre\"},\"Sum(RLTR_DATA.Acres)\":{\"displayName\":\"Average Acreage\"}},\"drillFilterOtherVisuals\":true,\"hasDefaultSort\":true,\"objects\":{\"legend\":[{\"properties\":{\"show\":{\"expr\":{\"Literal\":{\"Value\":\"false\"}}}}}]},\"vcObjects\":{\"title\":[{\"properties\":{\"text\":{\"expr\":{\"Literal\":{\"Value\":\"'# of Listings by Property Type'\"}}},\"alignment\":{\"expr\":{\"Literal\":{\"Value\":\"'center'\"}}}}}],\"background\":[{\"properties\":{\"show\":{\"expr\":{\"Literal\":{\"Value\":\"false\"}}}}}],\"visualTooltip\":[{\"properties\":{\"themedTitleFontColor\":{\"solid\":{\"color\":{\"expr\":{\"ThemeDataColor\":{\"ColorId\":0,\"Percent\":0}}}}},\"themedValueFontColor\":{\"solid\":{\"color\":{\"expr\":{\"ThemeDataColor\":{\"ColorId\":0,\"Percent\":0}}}}},\"actionFontColor\":{\"solid\":{\"color\":{\"expr\":{\"ThemeDataColor\":{\"ColorId\":0,\"Percent\":0}}}}},\"themedBackground\":{\"solid\":{\"color\":{\"expr\":{\"ThemeDataColor\":{\"ColorId\":1,\"Percent\":0}}}}},\"transparency\":{\"expr\":{\"Literal\":{\"Value\":\"25D\"}}}}}]}}}",
          "filters": "[]",
          "height": 264.16,
          "width": 452.15,
          "x": 828.12,
          "y": 128.40,
          "z": 16000.00
        },
        {
          "config": "{\"name\":\"f121bc0469995bdbc9f1\",\"layouts\":[{\"id\":0,\"position\":{\"x\":2.4573378839590445,\"y\":469.3515358361775,\"z\":18000,\"width\":194.74402730375428,\"height\":33.1740614334471,\"tabOrder\":18000}}],\"singleVisual\":{\"visualType\":\"shape\",\"drillFilterOtherVisuals\":true,\"objects\":{\"shape\":[{\"properties\":{\"tileShape\":{\"expr\":{\"Literal\":{\"Value\":\"'line'\"}}}}}],\"rotation\":[{\"properties\":{\"shapeAngle\":{\"expr\":{\"Literal\":{\"Value\":\"0L\"}}}}}],\"fill\":[{\"properties\":{\"fillColor\":{\"solid\":{\"color\":{\"expr\":{\"ThemeDataColor\":{\"ColorId\":0,\"Percent\":-0.1}}}}}},\"selector\":{\"id\":\"default\"}}],\"outline\":[{\"properties\":{\"show\":{\"expr\":{\"Literal\":{\"Value\":\"true\"}}}}},{\"properties\":{\"lineColor\":{\"solid\":{\"color\":{\"expr\":{\"ThemeDataColor\":{\"ColorId\":0,\"Percent\":-0.1}}}}}},\"selector\":{\"id\":\"default\"}}]}},\"howCreated\":\"InsertVisualButton\"}",
          "filters": "[]",
          "height": 33.17,
          "width": 194.74,
          "x": 2.46,
          "y": 469.35,
          "z": 18000.00
        }
      ],
      "width": 1280.00
    }
  ],
  "theme": "AccessibleNeutral"
}